bad_depend_example_arkadiy/__init__.py
bad_depend_example_arkadiy/main.py
bad_depend_example_arkadiy-1.3.dist-info/METADATA
bad_depend_example_arkadiy-1.3.dist-info/WHEEL
bad_depend_example_arkadiy-1.3.dist-info/top_level.txt
bad_depend_example_arkadiy-1.3.dist-info/RECORD
