Metadata-Version: 2.1
Name: bad-depend-example-arkadiy
Version: 1.3
Summary: A example Python package with bad dep
Home-page: UNKNOWN
License: UNKNOWN
Platform: UNKNOWN
Requires-Dist: numpy (==1.17.0)
Requires-Dist: pandas (==1.3.3)
